[{"Name":"Jason Holder ","Runs":"11","Balls":"15","Fours":"1","Sixes":"0","Sr":"73.33","Venue":"Abu Dhabi","Date":"Nov 8 2020","Result":"Capitals won by 17 runs"},{"Name":"Jason Holder ","Runs":"24","Balls":"20","Fours":"3","Sixes":"0","Sr":"120.00","Venue":"Abu Dhabi","Date":"Nov 6 2020","Result":"Sunrisers won by 6 wickets (with 2 balls remaining)"},{"Name":"Jason Holder ","Runs":"26","Balls":"10","Fours":"1","Sixes":"3","Sr":"260.00","Venue":"Sharjah","Date":"Oct 31 2020","Result":"Sunrisers won by 5 wickets (with 35 balls remaining)"},{"Name":"Jason Holder ","Runs":"5","Balls":"8","Fours":"0","Sixes":"0","Sr":"62.50","Venue":"Dubai","Date":"Oct 24 2020","Result":"Kings XI won by 12 runs"}]